setup.py
cos_lib3/__init__.py
cos_lib3/cos.py
cos_lib3.egg-info/PKG-INFO
cos_lib3.egg-info/SOURCES.txt
cos_lib3.egg-info/dependency_links.txt
cos_lib3.egg-info/not-zip-safe
cos_lib3.egg-info/requires.txt
cos_lib3.egg-info/top_level.txt