Metadata-Version: 1.0
Name: cos-lib3
Version: 0.2.0
Summary: an unofficial sdk for qcloud cos
Home-page: https://github.com/imu-hupeng/cos-python3-sdk
Author: hupeng
Author-email: hupeng@imudges.com
License: MIT License
Platform: UNKNOWN
